gadfastrouter/__init__.py
gadfastrouter/const/__init__.py
gadfastrouter/const/encoding.py
gadfastrouter/const/sizes.py
gadfastrouter/const/symbols.py
gadfastrouter/enums/__init__.py
gadfastrouter/enums/http.py
gadfastrouter/enums/logging.py
gadfastrouter/routing/__init__.py
gadfastrouter/routing/route.py
gadfastrouter/routing/router.py
gadfastrouter-0.0.1.dist-info/LICENSE
gadfastrouter-0.0.1.dist-info/METADATA
gadfastrouter-0.0.1.dist-info/WHEEL
gadfastrouter-0.0.1.dist-info/top_level.txt
gadfastrouter-0.0.1.dist-info/RECORD
