Metadata-Version: 2.1
Name: gadfastrouter
Version: 0.0.1
Summary: A FastAPI routing extension that provides detailed request/response logging
Home-page: https://github.com/AlexDemure/gadfastrouter
Author: Alexander Grishchenko
Author-email: alexanderdemure@gmail.com
Classifier: Programming Language :: Python :: 3
Classifier: License :: OSI Approved :: MIT License
Classifier: Operating System :: OS Independent
Requires-Python: >=3.8
License-File: LICENSE
Requires-Dist: fastapi
Requires-Dist: gadutils
